sortxml.py
sortxml-0.1.0.dist-info/LICENSE
sortxml-0.1.0.dist-info/METADATA
sortxml-0.1.0.dist-info/WHEEL
sortxml-0.1.0.dist-info/top_level.txt
sortxml-0.1.0.dist-info/RECORD
