Metadata-Version: 2.1
Name: sortxml
Version: 0.1.0
Summary: A simple XML element sorter
Home-page: https://www.github.com/kopachris/sortxml
Author: Chris Koch
Author-email: kopachris@gmail.com
License: BSD 3-Clause License
Keywords: xml,sort,tool
Classifier: Programming Language :: Python :: 3
Classifier: License :: OSI Approved :: BSD License
Classifier: Topic :: Text Processing :: Markup :: XML
Classifier: Topic :: Utilities
License-File: LICENSE
Requires-Dist: python-dateutil
